fastapisupport/__init__.py
fastapisupport/context.py
fastapisupport/middleware.py
psycopg2logger/__init__.py
psycopg2logger/cursorinterceptor.py
tcp/__init__.py
tcp/tcpwriter.py
tests/test_cursorinterceptor.py
psycopg2logger-0.4.0.dist-info/METADATA
psycopg2logger-0.4.0.dist-info/WHEEL
psycopg2logger-0.4.0.dist-info/top_level.txt
psycopg2logger-0.4.0.dist-info/RECORD
