Metadata-Version: 2.4
Name: psycopg2logger
Version: 0.4.0
Summary: Psycopg2 logging / profiling tool
Author-email: Lars Halvor Anundskås <larshalvoranundskas@gmail.com>
License: MIT
Requires-Python: >=3.9
Requires-Dist: requests>=2.31
Requires-Dist: psycopg2>=2.9.10
Requires-Dist: fastapi
Requires-Dist: pydantic
